mitemp_bt/__init__.py
mitemp_bt/mitemp_bt_poller.py
test/__init__.py
test/conftest.py
test/helper.py
test/integration_tests/__init__.py
test/integration_tests/test_bluepy_backend.py
test/integration_tests/test_demo.py
test/integration_tests/test_everything.py
test/integration_tests/test_gatttool_backend.py
test/unit_tests/__init__.py
test/unit_tests/test_mitemp_bt_poller.py
test/unit_tests/test_parse.py
test/unit_tests/test_versioncheck.py
mitemp_bt-0.0.5.dist-info/LICENSE
mitemp_bt-0.0.5.dist-info/METADATA
mitemp_bt-0.0.5.dist-info/WHEEL
mitemp_bt-0.0.5.dist-info/top_level.txt
mitemp_bt-0.0.5.dist-info/RECORD
