Metadata-Version: 2.1
Name: mitemp-bt
Version: 0.0.5
Summary: Library to read data from Mi Temperature and Humidity Sensor (V2) using Bluetooth LE with LCD display
Home-page: https://github.com/ratcashdev/mitemp
Author: ratcashdev
Author-email: developer@ratcash.net
License: MIT
Keywords: temperature and humidity sensor bluetooth low-energy ble
Platform: UNKNOWN
Classifier: Development Status :: 3 - Alpha
Classifier: Intended Audience :: Developers
Classifier: Topic :: System :: Hardware :: Hardware Drivers
Classifier: License :: OSI Approved :: MIT License
Classifier: Programming Language :: Python :: 3
Classifier: Programming Language :: Python :: 3.4
Classifier: Programming Language :: Python :: 3.5
Classifier: Programming Language :: Python :: 3.9
License-File: LICENSE
Requires-Dist: btlewrap (>=0.0.8)
Provides-Extra: testing
Requires-Dist: pytest ; extra == 'testing'
